{
  "Name": "Destroy All Humans! Path of the Furon",
  "DatabaseID": "14415",
  "ReleaseDate": "2008-12-01T00:00:00+00:00",
  "Overview": "Destroy All Humans! Path of the Furon is an action-adventure game developed by Sandblast Games and published by THQ. The game is set in the 1970s and is the fourth game in the Destroy All Humans! series, released December 1, 2008 in North America for the Xbox 360.[3][5] The game was developed by THQ's Sandblast Games studio for the Xbox 360 and PlayStation 3 consoles.[6] Path of the Furon expands on the open world format of the previous Destroy All Humans! games, with five new open worlds on the ground and in the air to obliterate with new weapons and new alien powers.\n\nOn November 26, 2008, the North American PlayStation 3 version was canceled citing \"development issues\".[7] However, the PlayStation 3 version was still released in Australia on February 12, 2009 and Europe on February 13, 2009 alongside the Xbox 360 release.[8]",
  "CommunityRating": "3.66666666666667",
  "ESRB": "T - Teen",
  "Genres": "Sandbox; Shooter",
  "Developer": "Sandblast Games",
  "Publisher": "THQ",
  "Artwork": {
    "Banner": [
      {
        "FileName": "675236f5-9dea-418c-bc71-3728c5d29461.png",
        "Type": "Banner",
        "CRC32": "3995230241",
        "URL": "http://images.launchbox-app.com/675236f5-9dea-418c-bc71-3728c5d29461.png"
      }
    ],
    "Background": [
      {
        "FileName": "ca4f0f0e-59c9-4017-8627-a8e7351c1af6.jpg",
        "Type": "Fanart - Background",
        "CRC32": "2433947020",
        "URL": "http://images.launchbox-app.com/ca4f0f0e-59c9-4017-8627-a8e7351c1af6.jpg"
      },
      {
        "FileName": "54f85ad1-badf-4f58-a587-ffb44046889a.jpg",
        "Type": "Fanart - Background",
        "CRC32": "2563635242",
        "URL": "http://images.launchbox-app.com/54f85ad1-badf-4f58-a587-ffb44046889a.jpg"
      },
      {
        "FileName": "27de26a7-5ccb-439e-8136-d80ebbc5216c.png",
        "Type": "Fanart - Background",
        "CRC32": "988749953",
        "URL": "http://images.launchbox-app.com/27de26a7-5ccb-439e-8136-d80ebbc5216c.png"
      }
    ],
    "Box": {
      "3D": [
        {
          "FileName": "5930e3cb-e396-42cc-848d-95b975782c0c.png",
          "Type": "Box - 3D",
          "Region": "North America",
          "CRC32": "1441837050",
          "URL": "http://images.launchbox-app.com/5930e3cb-e396-42cc-848d-95b975782c0c.png"
        }
      ],
      "Back": [
        {
          "FileName": "dad361fe-854f-4675-bc86-87b4cd68878f.jpg",
          "Type": "Box - Back",
          "Region": "North America",
          "CRC32": "741784802",
          "URL": "http://images.launchbox-app.com/dad361fe-854f-4675-bc86-87b4cd68878f.jpg"
        }
      ],
      "Front": [
        {
          "FileName": "efc78d1a-0114-4a61-a9d0-628e0af2b5e3.jpg",
          "Type": "Box - Front",
          "Region": "North America",
          "CRC32": "3162777737",
          "URL": "http://images.launchbox-app.com/efc78d1a-0114-4a61-a9d0-628e0af2b5e3.jpg"
        },
        {
          "FileName": "5feede2c-227c-4379-8185-2da04a623fe3.png",
          "Type": "Box - Front - Reconstructed",
          "Region": "North America",
          "CRC32": "1026561438",
          "URL": "http://images.launchbox-app.com/5feede2c-227c-4379-8185-2da04a623fe3.png"
        }
      ],
      "Spine": [
        {
          "FileName": "5ba55b49-dac0-4db2-af29-88b46056f4e5.jpg",
          "Type": "Box - Spine",
          "Region": "North America",
          "CRC32": "852239625",
          "URL": "http://images.launchbox-app.com/5ba55b49-dac0-4db2-af29-88b46056f4e5.jpg"
        }
      ]
    },
    "Disc": [
      {
        "FileName": "d45eca3f-f534-45c2-b130-117c9841894f.png",
        "Type": "Disc",
        "Region": "North America",
        "CRC32": "2347348967",
        "URL": "http://images.launchbox-app.com/d45eca3f-f534-45c2-b130-117c9841894f.png"
      }
    ],
    "Other": [
      {
        "FileName": "04aa3721-78e4-4d42-8691-6ff0393f94a3.png",
        "Type": "Clear Logo",
        "CRC32": "1229675937",
        "URL": "http://images.launchbox-app.com/04aa3721-78e4-4d42-8691-6ff0393f94a3.png"
      }
    ]
  }
}