{
    "id": "4E4207D4",
    "title": {
        "full": "Heroes",
        "reduced": "Heroes"
    },
    "genre": [
        "Independent & Music Videos",
        "TV Shows",
        "Xbox LIVE Marketplace"
    ],
    "developer": null,
    "publisher": "Nick Busby",
    "release_date": null,
    "user_rating": null,
    "description": {
        "full": "NBC's \"Heroes\", an epic drama that chronicles the lives of ordinary people who discover they possess extraordinary abilities.",
        "short": "NBC's \"Heroes\", an epic drama that chronicles the lives of ordinary people who discover they possess extraordinary abilities."
    },
    "media": [],
    "artwork": {
        "background": null,
        "banner": "http://avatar.xboxlive.com/global/t.4e4207d4/marketplace/0/1",
        "boxart": null,
        "icon": "http://avatar.xboxlive.com/global/t.4e4207d4/icon/0/8000",
        "gallery": []
    },
    "products": {
        "parent": [],
        "related": []
    }
}