{
  "Name": "Worms Revolution",
  "DatabaseID": "16154",
  "ReleaseDate": "2012-10-10T00:00:00+00:00",
  "Overview": "Worms Revolution is an artillery strategy game developed by Team17 and is part of the Worms series. It was released on PlayStation 3, Windows via Steam and Xbox 360 in October 2012. An OS X version was released on June 6, 2013. A PlayStation Vita version including all three previously released downloadable packs and titled Worms Revolution Extreme was released on October 8, 2013. Like previous games in the series, gameplay is 2D and turn-based, but it is rendered with an all-new 3D engine. There are both single player and multiplayer modes with up to four players online or local hotseat. The game was delisted from Xbox Live Arcade on June 2, 2015.",
  "CommunityRating": "3.375",
  "ESRB": "E10+ - Everyone 10+",
  "Genres": null,
  "Artwork": {
    "Box": {
      "Front": [
        {
          "FileName": "e4b719f6-a150-4d46-990a-9ba66de0ae33.jpg",
          "Type": "Box - Front",
          "Region": "World",
          "CRC32": "213419188",
          "URL": "http://images.launchbox-app.com/e4b719f6-a150-4d46-990a-9ba66de0ae33.jpg"
        }
      ]
    },
    "Other": [
      {
        "FileName": "f57e3cba-b993-4b22-96e0-2614c071ad32.png",
        "Type": "Clear Logo",
        "CRC32": "3346770801",
        "URL": "http://images.launchbox-app.com/f57e3cba-b993-4b22-96e0-2614c071ad32.png"
      }
    ]
  }
}