{
  "Name": "Double Dragon II: Wander of the Dragons",
  "DatabaseID": "203741",
  "ReleaseDate": "2013-04-05T00:00:00+00:00",
  "Overview": "Double Dragon II: Wander of the Dragons is a side-scrolling 3D beat-'em-up game based on both the arcade and NES versions of Double Dragon II: The Revenge, developed by Korean game studio GRAVITY and published by Barunson Creative Co. Ltd. The title was first announced in 2011, but was shelved for release for two years. It was eventually released on April 5, 2013 as a digital download for the Xbox 360 via the Xbox Live Arcade service.",
  "VideoURL": "https://www.youtube.com/watch?v=yQkRzNzHbEs",
  "CommunityRating": "3.18181818181818",
  "WikipediaURL": "https://en.wikipedia.org/wiki/Double_Dragon_II:_The_Revenge#Legacy",
  "ESRB": "T - Teen",
  "Genres": "Beat 'em Up",
  "Developer": "Gravity",
  "Publisher": "Barunson Creative",
  "Artwork": {
    "Banner": [
      {
        "FileName": "68d2b2c8-4385-4dab-93b4-185d0d8281cd.png",
        "Type": "Banner",
        "CRC32": "142905089",
        "URL": "http://images.launchbox-app.com/68d2b2c8-4385-4dab-93b4-185d0d8281cd.png"
      }
    ],
    "Background": [
      {
        "FileName": "a1977f2d-babc-4283-8fe3-1c935f0fc830.jpg",
        "Type": "Fanart - Background",
        "CRC32": "3647101702",
        "URL": "http://images.launchbox-app.com/a1977f2d-babc-4283-8fe3-1c935f0fc830.jpg"
      }
    ],
    "Box": {
      "Front": [
        {
          "FileName": "1880d8bd-604b-4001-8dee-516d5c95416f.png",
          "Type": "Box - Front",
          "Region": "North America",
          "CRC32": "2644967911",
          "URL": "http://images.launchbox-app.com/1880d8bd-604b-4001-8dee-516d5c95416f.png"
        },
        {
          "FileName": "1d860a6d-251d-4715-a65b-d950bd4c1aa6.jpg",
          "Type": "Box - Front",
          "Region": "North America",
          "CRC32": "1598265026",
          "URL": "http://images.launchbox-app.com/1d860a6d-251d-4715-a65b-d950bd4c1aa6.jpg"
        }
      ]
    },
    "Screenshots": [
      {
        "FileName": "81437cb2-de4d-4cfe-95cc-bf2621d801e2.jpg",
        "Type": "Screenshot - Gameplay",
        "CRC32": "156339992",
        "URL": "http://images.launchbox-app.com/81437cb2-de4d-4cfe-95cc-bf2621d801e2.jpg"
      },
      {
        "FileName": "e73b4320-31bb-421b-bfa0-f625bd3032c1.jpg",
        "Type": "Screenshot - Gameplay",
        "CRC32": "2812525141",
        "URL": "http://images.launchbox-app.com/e73b4320-31bb-421b-bfa0-f625bd3032c1.jpg"
      },
      {
        "FileName": "2edabc50-c99d-4829-83e6-40c62bfbf65f.jpg",
        "Type": "Screenshot - Gameplay",
        "CRC32": "2733396743",
        "URL": "http://images.launchbox-app.com/2edabc50-c99d-4829-83e6-40c62bfbf65f.jpg"
      },
      {
        "FileName": "a9be1b3f-72b5-4611-94d9-8c89f18e7b20.jpg",
        "Type": "Screenshot - Gameplay",
        "CRC32": "4023836563",
        "URL": "http://images.launchbox-app.com/a9be1b3f-72b5-4611-94d9-8c89f18e7b20.jpg"
      },
      {
        "FileName": "04c69f63-7252-441e-b8dd-e1965085f6c8.jpg",
        "Type": "Screenshot - Gameplay",
        "CRC32": "1315216409",
        "URL": "http://images.launchbox-app.com/04c69f63-7252-441e-b8dd-e1965085f6c8.jpg"
      },
      {
        "FileName": "5ccd490a-43bc-4f64-9cbf-1952f69e357b.jpg",
        "Type": "Screenshot - Gameplay",
        "CRC32": "3428416029",
        "URL": "http://images.launchbox-app.com/5ccd490a-43bc-4f64-9cbf-1952f69e357b.jpg"
      },
      {
        "FileName": "96c48636-59f5-4e80-80b3-d412631ff223.jpg",
        "Type": "Screenshot - Gameplay",
        "CRC32": "4088230420",
        "URL": "http://images.launchbox-app.com/96c48636-59f5-4e80-80b3-d412631ff223.jpg"
      },
      {
        "FileName": "c55ca18d-9683-4db1-8e69-918725a59092.jpg",
        "Type": "Screenshot - Gameplay",
        "CRC32": "1600698573",
        "URL": "http://images.launchbox-app.com/c55ca18d-9683-4db1-8e69-918725a59092.jpg"
      }
    ]
  }
}